<?xml version="1.0" encoding="UTF-8"?>

<!-- generated on 2023-07-19 16:42:02 by Eclipse SUMO sumo Version 1.17.0
<configuration xmlns:xsi="http://www.w3.org/2001/XMLSchema-instance" xsi:noNamespaceSchemaLocation="http://sumo.dlr.de/xsd/sumoConfiguration.xsd">

    <input>
        <net-file value="Data0-0\intersection.net.xml"/>
        <route-files value="Data0-0\intersection.rou.xml"/>
        <additional-files value="Data0-0\intersection.det.xml"/>
    </input>

    <output>
        <tripinfo-output value="Data0-0\tripinfo.xml"/>
    </output>

    <time>
        <begin value="0"/>
    </time>

    <processing>
        <time-to-teleport value="-1"/>
        <waiting-time-memory value="60000"/>
    </processing>

    <report>
        <verbose value="true"/>
        <no-step-log value="true"/>
    </report>

    <traci_server>
        <remote-port value="62931"/>
    </traci_server>

    <gui_only>
        <gui-settings-file value="Data0-0\intersection.settings.xml"/>
    </gui_only>

</configuration>
-->

<detector xmlns:xsi="http://www.w3.org/2001/XMLSchema-instance" xsi:noNamespaceSchemaLocation="http://sumo.dlr.de/xsd/det_e2_file.xsd">
   <interval begin="0.00" end="100.00" id="FlaneAreaDetector.N0" sampledSeconds="285.47" nVehEntered="12" nVehLeft="9" nVehSeen="12" meanSpeed="13.39" meanTimeLoss="0.86" meanOccupancy="1.81" maxOccupancy="3.21" meanMaxJamLengthInVehicles="0.00" meanMaxJamLengthInMeters="0.00" maxJamLengthInVehicles="0" maxJamLengthInMeters="0.00" jamLengthInVehiclesSum="0" jamLengthInMetersSum="0.00" meanHaltingDuration="0.00" maxHaltingDuration="0.00" haltingDurationSum="0.00" meanIntervalHaltingDuration="0.00" maxIntervalHaltingDuration="0.00" intervalHaltingDurationSum="0.00" startedHalts="0.00" meanVehicleNumber="2.86" maxVehicleNumber="5" />
   <interval begin="100.00" end="200.00" id="FlaneAreaDetector.N0" sampledSeconds="109.14" nVehEntered="9" nVehLeft="10" nVehSeen="12" meanSpeed="13.28" meanTimeLoss="0.42" meanOccupancy="0.69" maxOccupancy="2.56" meanMaxJamLengthInVehicles="0.00" meanMaxJamLengthInMeters="0.00" maxJamLengthInVehicles="0" maxJamLengthInMeters="0.00" jamLengthInVehiclesSum="0" jamLengthInMetersSum="0.00" meanHaltingDuration="0.00" maxHaltingDuration="0.00" haltingDurationSum="0.00" meanIntervalHaltingDuration="0.00" maxIntervalHaltingDuration="0.00" intervalHaltingDurationSum="0.00" startedHalts="0.00" meanVehicleNumber="1.10" maxVehicleNumber="4" />
   <interval begin="200.00" end="300.00" id="FlaneAreaDetector.N0" sampledSeconds="456.09" nVehEntered="13" nVehLeft="10" nVehSeen="15" meanSpeed="12.68" meanTimeLoss="1.82" meanOccupancy="2.89" maxOccupancy="4.49" meanMaxJamLengthInVehicles="0.04" meanMaxJamLengthInMeters="0.20" maxJamLengthInVehicles="1" maxJamLengthInMeters="5.00" jamLengthInVehiclesSum="4" jamLengthInMetersSum="20.00" meanHaltingDuration="5.00" maxHaltingDuration="5.00" haltingDurationSum="5.00" meanIntervalHaltingDuration="5.00" maxIntervalHaltingDuration="5.00" intervalHaltingDurationSum="5.00" startedHalts="1.00" meanVehicleNumber="4.59" maxVehicleNumber="7" />
   <interval begin="300.00" end="400.00" id="FlaneAreaDetector.N0" sampledSeconds="714.04" nVehEntered="20" nVehLeft="17" nVehSeen="25" meanSpeed="12.39" meanTimeLoss="2.86" meanOccupancy="4.51" maxOccupancy="5.77" meanMaxJamLengthInVehicles="0.17" meanMaxJamLengthInMeters="0.82" maxJamLengthInVehicles="1" maxJamLengthInMeters="5.00" jamLengthInVehiclesSum="17" jamLengthInMetersSum="81.90" meanHaltingDuration="3.12" maxHaltingDuration="5.00" haltingDurationSum="25.00" meanIntervalHaltingDuration="3.12" maxIntervalHaltingDuration="5.00" intervalHaltingDurationSum="25.00" startedHalts="8.00" meanVehicleNumber="7.19" maxVehicleNumber="9" />
   <interval begin="400.00" end="500.00" id="FlaneAreaDetector.N0" sampledSeconds="625.68" nVehEntered="13" nVehLeft="18" nVehSeen="21" meanSpeed="11.14" meanTimeLoss="3.78" meanOccupancy="3.92" maxOccupancy="6.41" meanMaxJamLengthInVehicles="0.15" meanMaxJamLengthInMeters="0.76" maxJamLengthInVehicles="2" maxJamLengthInMeters="12.53" jamLengthInVehiclesSum="15" jamLengthInMetersSum="75.56" meanHaltingDuration="2.36" maxHaltingDuration="5.00" haltingDurationSum="26.00" meanIntervalHaltingDuration="2.36" maxIntervalHaltingDuration="5.00" intervalHaltingDurationSum="26.00" startedHalts="11.00" meanVehicleNumber="6.33" maxVehicleNumber="10" />
   <interval begin="500.00" end="600.00" id="FlaneAreaDetector.N0" sampledSeconds="707.96" nVehEntered="26" nVehLeft="20" nVehSeen="29" meanSpeed="12.71" meanTimeLoss="2.06" meanOccupancy="4.49" maxOccupancy="7.05" meanMaxJamLengthInVehicles="0.14" meanMaxJamLengthInMeters="0.69" maxJamLengthInVehicles="1" maxJamLengthInMeters="5.00" jamLengthInVehiclesSum="14" jamLengthInMetersSum="69.02" meanHaltingDuration="3.80" maxHaltingDuration="8.00" haltingDurationSum="19.00" meanIntervalHaltingDuration="3.80" maxIntervalHaltingDuration="8.00" intervalHaltingDurationSum="19.00" startedHalts="5.00" meanVehicleNumber="7.10" maxVehicleNumber="11" />
   <interval begin="600.00" end="700.00" id="FlaneAreaDetector.N0" sampledSeconds="851.74" nVehEntered="12" nVehLeft="12" nVehSeen="21" meanSpeed="6.67" meanTimeLoss="21.03" meanOccupancy="5.43" maxOccupancy="7.05" meanMaxJamLengthInVehicles="3.69" meanMaxJamLengthInMeters="25.31" maxJamLengthInVehicles="7" maxJamLengthInMeters="50.08" jamLengthInVehiclesSum="370" jamLengthInMetersSum="2536.00" meanHaltingDuration="18.14" maxHaltingDuration="51.00" haltingDurationSum="399.00" meanIntervalHaltingDuration="17.77" maxIntervalHaltingDuration="51.00" intervalHaltingDurationSum="391.00" startedHalts="21.00" meanVehicleNumber="8.54" maxVehicleNumber="11" />
   <interval begin="700.00" end="800.00" id="FlaneAreaDetector.N0" sampledSeconds="1095.79" nVehEntered="14" nVehLeft="11" nVehSeen="23" meanSpeed="4.61" meanTimeLoss="31.80" meanOccupancy="6.99" maxOccupancy="8.33" meanMaxJamLengthInVehicles="6.39" meanMaxJamLengthInMeters="45.57" maxJamLengthInVehicles="10" maxJamLengthInMeters="72.52" jamLengthInVehiclesSum="646" jamLengthInMetersSum="4592.42" meanHaltingDuration="29.22" maxHaltingDuration="71.00" haltingDurationSum="935.00" meanIntervalHaltingDuration="20.97" maxIntervalHaltingDuration="71.00" intervalHaltingDurationSum="671.00" startedHalts="25.00" meanVehicleNumber="10.99" maxVehicleNumber="13" />
   <interval begin="800.00" end="900.00" id="FlaneAreaDetector.N0" sampledSeconds="511.14" nVehEntered="14" nVehLeft="21" nVehSeen="26" meanSpeed="10.52" meanTimeLoss="3.61" meanOccupancy="3.20" maxOccupancy="7.69" meanMaxJamLengthInVehicles="0.22" meanMaxJamLengthInMeters="1.35" maxJamLengthInVehicles="4" maxJamLengthInMeters="28.99" jamLengthInVehiclesSum="25" jamLengthInMetersSum="149.69" meanHaltingDuration="12.71" maxHaltingDuration="63.00" haltingDurationSum="178.00" meanIntervalHaltingDuration="2.43" maxIntervalHaltingDuration="4.00" intervalHaltingDurationSum="34.00" startedHalts="9.00" meanVehicleNumber="5.16" maxVehicleNumber="13" />
   <interval begin="900.00" end="1000.00" id="FlaneAreaDetector.N0" sampledSeconds="597.95" nVehEntered="17" nVehLeft="17" nVehSeen="22" meanSpeed="12.05" meanTimeLoss="2.32" meanOccupancy="3.77" maxOccupancy="5.77" meanMaxJamLengthInVehicles="0.06" meanMaxJamLengthInMeters="0.28" maxJamLengthInVehicles="1" maxJamLengthInMeters="5.00" jamLengthInVehiclesSum="6" jamLengthInMetersSum="27.71" meanHaltingDuration="2.00" maxHaltingDuration="3.00" haltingDurationSum="12.00" meanIntervalHaltingDuration="2.00" maxIntervalHaltingDuration="3.00" intervalHaltingDurationSum="12.00" startedHalts="6.00" meanVehicleNumber="6.04" maxVehicleNumber="9" />
   <interval begin="1000.00" end="1100.00" id="FlaneAreaDetector.N0" sampledSeconds="450.33" nVehEntered="12" nVehLeft="12" nVehSeen="17" meanSpeed="10.34" meanTimeLoss="5.89" meanOccupancy="2.84" maxOccupancy="4.38" meanMaxJamLengthInVehicles="0.54" meanMaxJamLengthInMeters="2.79" maxJamLengthInVehicles="2" maxJamLengthInMeters="12.53" jamLengthInVehiclesSum="54" jamLengthInMetersSum="279.19" meanHaltingDuration="7.11" maxHaltingDuration="34.00" haltingDurationSum="64.00" meanIntervalHaltingDuration="6.89" maxIntervalHaltingDuration="34.00" intervalHaltingDurationSum="62.00" startedHalts="8.00" meanVehicleNumber="4.54" maxVehicleNumber="7" />
   <interval begin="1100.00" end="1200.00" id="FlaneAreaDetector.N0" sampledSeconds="482.04" nVehEntered="11" nVehLeft="12" nVehSeen="16" meanSpeed="10.81" meanTimeLoss="5.45" meanOccupancy="3.01" maxOccupancy="4.49" meanMaxJamLengthInVehicles="0.33" meanMaxJamLengthInMeters="1.78" maxJamLengthInVehicles="2" maxJamLengthInMeters="12.59" jamLengthInVehiclesSum="33" jamLengthInMetersSum="178.31" meanHaltingDuration="3.36" maxHaltingDuration="8.00" haltingDurationSum="47.00" meanIntervalHaltingDuration="3.29" maxIntervalHaltingDuration="8.00" intervalHaltingDurationSum="46.00" startedHalts="13.00" meanVehicleNumber="4.88" maxVehicleNumber="7" />
   <interval begin="1200.00" end="1300.00" id="FlaneAreaDetector.N0" sampledSeconds="763.92" nVehEntered="14" nVehLeft="11" nVehSeen="18" meanSpeed="10.05" meanTimeLoss="10.67" meanOccupancy="4.84" maxOccupancy="6.41" meanMaxJamLengthInVehicles="1.34" meanMaxJamLengthInMeters="8.20" maxJamLengthInVehicles="3" maxJamLengthInMeters="21.30" jamLengthInVehiclesSum="134" jamLengthInMetersSum="820.17" meanHaltingDuration="13.08" maxHaltingDuration="51.00" haltingDurationSum="157.00" meanIntervalHaltingDuration="12.00" maxIntervalHaltingDuration="51.00" intervalHaltingDurationSum="144.00" startedHalts="10.00" meanVehicleNumber="7.69" maxVehicleNumber="10" />
   <interval begin="1300.00" end="1400.00" id="FlaneAreaDetector.N0" sampledSeconds="614.75" nVehEntered="13" nVehLeft="13" nVehSeen="20" meanSpeed="12.57" meanTimeLoss="2.33" meanOccupancy="3.87" maxOccupancy="5.13" meanMaxJamLengthInVehicles="0.08" meanMaxJamLengthInMeters="0.37" maxJamLengthInVehicles="1" maxJamLengthInMeters="5.00" jamLengthInVehiclesSum="8" jamLengthInMetersSum="36.73" meanHaltingDuration="3.00" maxHaltingDuration="4.00" haltingDurationSum="12.00" meanIntervalHaltingDuration="3.00" maxIntervalHaltingDuration="4.00" intervalHaltingDurationSum="12.00" startedHalts="4.00" meanVehicleNumber="6.21" maxVehicleNumber="8" />
   <interval begin="1400.00" end="1500.00" id="FlaneAreaDetector.N0" sampledSeconds="265.24" nVehEntered="6" nVehLeft="10" nVehSeen="13" meanSpeed="12.00" meanTimeLoss="1.00" meanOccupancy="1.66" maxOccupancy="4.49" meanMaxJamLengthInVehicles="0.00" meanMaxJamLengthInMeters="0.00" maxJamLengthInVehicles="0" maxJamLengthInMeters="0.00" jamLengthInVehiclesSum="0" jamLengthInMetersSum="0.00" meanHaltingDuration="0.00" maxHaltingDuration="0.00" haltingDurationSum="0.00" meanIntervalHaltingDuration="0.00" maxIntervalHaltingDuration="0.00" intervalHaltingDurationSum="0.00" startedHalts="0.00" meanVehicleNumber="2.68" maxVehicleNumber="7" />
   <interval begin="1500.00" end="1600.00" id="FlaneAreaDetector.N0" sampledSeconds="463.76" nVehEntered="10" nVehLeft="6" nVehSeen="13" meanSpeed="12.52" meanTimeLoss="1.88" meanOccupancy="2.95" maxOccupancy="4.49" meanMaxJamLengthInVehicles="0.03" meanMaxJamLengthInMeters="0.14" maxJamLengthInVehicles="1" maxJamLengthInMeters="5.00" jamLengthInVehiclesSum="3" jamLengthInMetersSum="14.00" meanHaltingDuration="4.00" maxHaltingDuration="4.00" haltingDurationSum="4.00" meanIntervalHaltingDuration="4.00" maxIntervalHaltingDuration="4.00" intervalHaltingDurationSum="4.00" startedHalts="1.00" meanVehicleNumber="4.66" maxVehicleNumber="8" />
   <interval begin="1600.00" end="1700.00" id="FlaneAreaDetector.N0" sampledSeconds="322.29" nVehEntered="3" nVehLeft="9" nVehSeen="10" meanSpeed="12.27" meanTimeLoss="2.65" meanOccupancy="2.02" maxOccupancy="4.49" meanMaxJamLengthInVehicles="0.04" meanMaxJamLengthInMeters="0.19" maxJamLengthInVehicles="1" maxJamLengthInMeters="5.00" jamLengthInVehiclesSum="4" jamLengthInMetersSum="18.89" meanHaltingDuration="2.33" maxHaltingDuration="5.00" haltingDurationSum="7.00" meanIntervalHaltingDuration="2.33" maxIntervalHaltingDuration="5.00" intervalHaltingDurationSum="7.00" startedHalts="3.00" meanVehicleNumber="3.25" maxVehicleNumber="7" />
   <interval begin="1700.00" end="1800.00" id="FlaneAreaDetector.N0" sampledSeconds="199.94" nVehEntered="8" nVehLeft="6" nVehSeen="9" meanSpeed="10.99" meanTimeLoss="3.33" meanOccupancy="1.27" maxOccupancy="1.92" meanMaxJamLengthInVehicles="0.20" meanMaxJamLengthInMeters="1.00" maxJamLengthInVehicles="1" maxJamLengthInMeters="5.00" jamLengthInVehiclesSum="20" jamLengthInMetersSum="100.00" meanHaltingDuration="21.00" maxHaltingDuration="21.00" haltingDurationSum="21.00" meanIntervalHaltingDuration="21.00" maxIntervalHaltingDuration="21.00" intervalHaltingDurationSum="21.00" startedHalts="1.00" meanVehicleNumber="2.01" maxVehicleNumber="3" />
   <interval begin="1800.00" end="1900.00" id="FlaneAreaDetector.N0" sampledSeconds="377.11" nVehEntered="15" nVehLeft="12" nVehSeen="18" meanSpeed="11.63" meanTimeLoss="2.02" meanOccupancy="2.38" maxOccupancy="3.85" meanMaxJamLengthInVehicles="0.06" meanMaxJamLengthInMeters="0.28" maxJamLengthInVehicles="1" maxJamLengthInMeters="5.00" jamLengthInVehiclesSum="6" jamLengthInMetersSum="27.84" meanHaltingDuration="2.20" maxHaltingDuration="4.00" haltingDurationSum="11.00" meanIntervalHaltingDuration="2.20" maxIntervalHaltingDuration="4.00" intervalHaltingDurationSum="11.00" startedHalts="5.00" meanVehicleNumber="3.80" maxVehicleNumber="6" />
   <interval begin="1900.00" end="2000.00" id="FlaneAreaDetector.N0" sampledSeconds="660.48" nVehEntered="21" nVehLeft="20" nVehSeen="27" meanSpeed="12.64" meanTimeLoss="1.35" meanOccupancy="4.19" maxOccupancy="5.13" meanMaxJamLengthInVehicles="0.05" meanMaxJamLengthInMeters="0.24" maxJamLengthInVehicles="1" maxJamLengthInMeters="5.00" jamLengthInVehiclesSum="5" jamLengthInMetersSum="23.95" meanHaltingDuration="3.50" maxHaltingDuration="4.00" haltingDurationSum="7.00" meanIntervalHaltingDuration="3.50" maxIntervalHaltingDuration="4.00" intervalHaltingDurationSum="7.00" startedHalts="2.00" meanVehicleNumber="6.64" maxVehicleNumber="8" />
   <interval begin="2000.00" end="2100.00" id="FlaneAreaDetector.N0" sampledSeconds="501.13" nVehEntered="14" nVehLeft="18" nVehSeen="21" meanSpeed="11.40" meanTimeLoss="3.70" meanOccupancy="3.12" maxOccupancy="5.13" meanMaxJamLengthInVehicles="0.21" meanMaxJamLengthInMeters="1.04" maxJamLengthInVehicles="2" maxJamLengthInMeters="12.65" jamLengthInVehiclesSum="21" jamLengthInMetersSum="104.16" meanHaltingDuration="2.91" maxHaltingDuration="4.00" haltingDurationSum="32.00" meanIntervalHaltingDuration="2.91" maxIntervalHaltingDuration="4.00" intervalHaltingDurationSum="32.00" startedHalts="11.00" meanVehicleNumber="5.09" maxVehicleNumber="8" />
   <interval begin="2100.00" end="2200.00" id="FlaneAreaDetector.N0" sampledSeconds="469.69" nVehEntered="11" nVehLeft="8" nVehSeen="14" meanSpeed="10.86" meanTimeLoss="6.76" meanOccupancy="2.98" maxOccupancy="4.49" meanMaxJamLengthInVehicles="0.68" meanMaxJamLengthInMeters="4.20" maxJamLengthInVehicles="2" maxJamLengthInMeters="12.53" jamLengthInVehiclesSum="68" jamLengthInMetersSum="420.07" meanHaltingDuration="23.67" maxHaltingDuration="35.00" haltingDurationSum="71.00" meanIntervalHaltingDuration="23.67" maxIntervalHaltingDuration="35.00" intervalHaltingDurationSum="71.00" startedHalts="3.00" meanVehicleNumber="4.73" maxVehicleNumber="7" />
   <interval begin="2200.00" end="2300.00" id="FlaneAreaDetector.N0" sampledSeconds="615.19" nVehEntered="17" nVehLeft="17" nVehSeen="23" meanSpeed="12.46" meanTimeLoss="2.06" meanOccupancy="3.90" maxOccupancy="5.13" meanMaxJamLengthInVehicles="0.11" meanMaxJamLengthInMeters="0.55" maxJamLengthInVehicles="1" maxJamLengthInMeters="5.00" jamLengthInVehiclesSum="11" jamLengthInMetersSum="55.00" meanHaltingDuration="4.67" maxHaltingDuration="10.00" haltingDurationSum="14.00" meanIntervalHaltingDuration="4.67" maxIntervalHaltingDuration="10.00" intervalHaltingDurationSum="14.00" startedHalts="3.00" meanVehicleNumber="6.20" maxVehicleNumber="8" />
   <interval begin="2300.00" end="2400.00" id="FlaneAreaDetector.N0" sampledSeconds="629.14" nVehEntered="19" nVehLeft="19" nVehSeen="25" meanSpeed="10.24" meanTimeLoss="5.75" meanOccupancy="3.96" maxOccupancy="5.77" meanMaxJamLengthInVehicles="0.89" meanMaxJamLengthInMeters="5.71" maxJamLengthInVehicles="4" maxJamLengthInMeters="27.57" jamLengthInVehiclesSum="89" jamLengthInMetersSum="570.59" meanHaltingDuration="9.91" maxHaltingDuration="35.00" haltingDurationSum="109.00" meanIntervalHaltingDuration="9.00" maxIntervalHaltingDuration="25.00" intervalHaltingDurationSum="99.00" startedHalts="10.00" meanVehicleNumber="6.35" maxVehicleNumber="9" />
   <interval begin="2400.00" end="2500.00" id="FlaneAreaDetector.N0" sampledSeconds="626.82" nVehEntered="15" nVehLeft="15" nVehSeen="21" meanSpeed="10.72" meanTimeLoss="6.92" meanOccupancy="3.97" maxOccupancy="5.13" meanMaxJamLengthInVehicles="0.99" meanMaxJamLengthInMeters="6.24" maxJamLengthInVehicles="3" maxJamLengthInMeters="20.03" jamLengthInVehiclesSum="99" jamLengthInMetersSum="624.32" meanHaltingDuration="12.00" maxHaltingDuration="40.00" haltingDurationSum="108.00" meanIntervalHaltingDuration="12.00" maxIntervalHaltingDuration="40.00" intervalHaltingDurationSum="108.00" startedHalts="9.00" meanVehicleNumber="6.30" maxVehicleNumber="8" />
   <interval begin="2500.00" end="2600.00" id="FlaneAreaDetector.N0" sampledSeconds="586.71" nVehEntered="16" nVehLeft="17" nVehSeen="22" meanSpeed="9.58" meanTimeLoss="6.56" meanOccupancy="3.67" maxOccupancy="5.13" meanMaxJamLengthInVehicles="0.79" meanMaxJamLengthInMeters="5.07" maxJamLengthInVehicles="4" maxJamLengthInMeters="27.50" jamLengthInVehiclesSum="79" jamLengthInMetersSum="507.02" meanHaltingDuration="11.06" maxHaltingDuration="46.00" haltingDurationSum="188.00" meanIntervalHaltingDuration="5.41" maxIntervalHaltingDuration="13.00" intervalHaltingDurationSum="92.00" startedHalts="13.00" meanVehicleNumber="5.93" maxVehicleNumber="9" />
   <interval begin="2600.00" end="2700.00" id="FlaneAreaDetector.N0" sampledSeconds="837.12" nVehEntered="22" nVehLeft="19" nVehSeen="27" meanSpeed="10.03" meanTimeLoss="7.38" meanOccupancy="5.31" maxOccupancy="8.12" meanMaxJamLengthInVehicles="1.33" meanMaxJamLengthInMeters="8.47" maxJamLengthInVehicles="4" maxJamLengthInMeters="27.51" jamLengthInVehiclesSum="133" jamLengthInMetersSum="846.63" meanHaltingDuration="13.09" maxHaltingDuration="31.00" haltingDurationSum="144.00" meanIntervalHaltingDuration="13.09" maxIntervalHaltingDuration="31.00" intervalHaltingDurationSum="144.00" startedHalts="11.00" meanVehicleNumber="8.43" maxVehicleNumber="13" />
   <interval begin="2700.00" end="2800.00" id="FlaneAreaDetector.N0" sampledSeconds="512.82" nVehEntered="12" nVehLeft="15" nVehSeen="20" meanSpeed="10.80" meanTimeLoss="3.65" meanOccupancy="3.21" maxOccupancy="5.13" meanMaxJamLengthInVehicles="0.16" meanMaxJamLengthInMeters="0.82" maxJamLengthInVehicles="2" maxJamLengthInMeters="12.66" jamLengthInVehiclesSum="16" jamLengthInMetersSum="81.55" meanHaltingDuration="2.60" maxHaltingDuration="5.00" haltingDurationSum="26.00" meanIntervalHaltingDuration="2.60" maxIntervalHaltingDuration="5.00" intervalHaltingDurationSum="26.00" startedHalts="10.00" meanVehicleNumber="5.20" maxVehicleNumber="8" />
</detector>
