<?xml version="1.0" encoding="UTF-8"?>

<!-- generated on 2023-07-30 20:16:27 by Eclipse SUMO sumo Version 1.17.0
<configuration xmlns:xsi="http://www.w3.org/2001/XMLSchema-instance" xsi:noNamespaceSchemaLocation="http://sumo.dlr.de/xsd/sumoConfiguration.xsd">

    <input>
        <net-file value="Data0-0\intersection.net.xml"/>
        <route-files value="Data0-0\intersection.rou.xml"/>
        <additional-files value="Data0-0\intersection.det.xml"/>
    </input>

    <output>
        <tripinfo-output value="Data0-0\tripinfo.xml"/>
    </output>

    <time>
        <begin value="0"/>
    </time>

    <processing>
        <time-to-teleport value="-1"/>
        <waiting-time-memory value="60000"/>
    </processing>

    <report>
        <verbose value="true"/>
        <no-step-log value="true"/>
    </report>

    <emissions>
        <device.emissions.probability value="1.0"/>
    </emissions>

    <traci_server>
        <remote-port value="50892"/>
    </traci_server>

    <gui_only>
        <gui-settings-file value="Data0-0\intersection.settings.xml"/>
    </gui_only>

</configuration>
-->

<detector xmlns:xsi="http://www.w3.org/2001/XMLSchema-instance" xsi:noNamespaceSchemaLocation="http://sumo.dlr.de/xsd/det_e2_file.xsd">
   <interval begin="0.00" end="100.00" id="laneAreaDetector.E3" sampledSeconds="32.21" nVehEntered="2" nVehLeft="2" nVehSeen="2" meanSpeed="7.11" meanTimeLoss="8.85" meanOccupancy="0.76" maxOccupancy="5.00" meanMaxJamLengthInVehicles="0.07" meanMaxJamLengthInMeters="0.35" maxJamLengthInVehicles="1" maxJamLengthInMeters="5.00" jamLengthInVehiclesSum="7" jamLengthInMetersSum="35.00" meanHaltingDuration="4.50" maxHaltingDuration="6.00" haltingDurationSum="9.00" meanIntervalHaltingDuration="4.50" maxIntervalHaltingDuration="6.00" intervalHaltingDurationSum="9.00" startedHalts="2.00" meanVehicleNumber="0.34" maxVehicleNumber="2" />
   <interval begin="100.00" end="200.00" id="laneAreaDetector.E3" sampledSeconds="106.61" nVehEntered="5" nVehLeft="5" nVehSeen="5" meanSpeed="1.50" meanTimeLoss="18.98" meanOccupancy="2.54" maxOccupancy="10.00" meanMaxJamLengthInVehicles="0.73" meanMaxJamLengthInMeters="4.71" maxJamLengthInVehicles="4" maxJamLengthInMeters="28.50" jamLengthInVehiclesSum="73" jamLengthInMetersSum="470.73" meanHaltingDuration="19.25" maxHaltingDuration="30.00" haltingDurationSum="77.00" meanIntervalHaltingDuration="19.25" maxIntervalHaltingDuration="30.00" intervalHaltingDurationSum="77.00" startedHalts="4.00" meanVehicleNumber="1.10" maxVehicleNumber="4" />
   <interval begin="200.00" end="300.00" id="laneAreaDetector.E3" sampledSeconds="80.62" nVehEntered="7" nVehLeft="7" nVehSeen="7" meanSpeed="2.41" meanTimeLoss="9.60" meanOccupancy="1.85" maxOccupancy="8.63" meanMaxJamLengthInVehicles="0.37" meanMaxJamLengthInMeters="2.22" maxJamLengthInVehicles="3" maxJamLengthInMeters="21.00" jamLengthInVehiclesSum="37" jamLengthInMetersSum="222.28" meanHaltingDuration="8.40" maxHaltingDuration="19.00" haltingDurationSum="42.00" meanIntervalHaltingDuration="8.40" maxIntervalHaltingDuration="19.00" intervalHaltingDurationSum="42.00" startedHalts="5.00" meanVehicleNumber="0.83" maxVehicleNumber="4" />
   <interval begin="300.00" end="400.00" id="laneAreaDetector.E3" sampledSeconds="39.40" nVehEntered="4" nVehLeft="4" nVehSeen="4" meanSpeed="4.03" meanTimeLoss="7.23" meanOccupancy="0.93" maxOccupancy="5.00" meanMaxJamLengthInVehicles="0.20" meanMaxJamLengthInMeters="1.03" maxJamLengthInVehicles="2" maxJamLengthInMeters="12.68" jamLengthInVehiclesSum="20" jamLengthInMetersSum="102.68" meanHaltingDuration="11.00" maxHaltingDuration="18.00" haltingDurationSum="22.00" meanIntervalHaltingDuration="11.00" maxIntervalHaltingDuration="18.00" intervalHaltingDurationSum="22.00" startedHalts="2.00" meanVehicleNumber="0.41" maxVehicleNumber="2" />
   <interval begin="400.00" end="500.00" id="laneAreaDetector.E3" sampledSeconds="228.99" nVehEntered="7" nVehLeft="7" nVehSeen="7" meanSpeed="1.87" meanTimeLoss="28.79" meanOccupancy="5.59" maxOccupancy="15.00" meanMaxJamLengthInVehicles="1.68" meanMaxJamLengthInMeters="11.24" maxJamLengthInVehicles="6" maxJamLengthInMeters="43.51" jamLengthInVehiclesSum="168" jamLengthInMetersSum="1123.70" meanHaltingDuration="29.00" maxHaltingDuration="51.00" haltingDurationSum="174.00" meanIntervalHaltingDuration="29.00" maxIntervalHaltingDuration="51.00" intervalHaltingDurationSum="174.00" startedHalts="6.00" meanVehicleNumber="2.33" maxVehicleNumber="6" />
   <interval begin="500.00" end="600.00" id="laneAreaDetector.E3" sampledSeconds="85.24" nVehEntered="5" nVehLeft="5" nVehSeen="5" meanSpeed="2.05" meanTimeLoss="14.70" meanOccupancy="2.02" maxOccupancy="8.65" meanMaxJamLengthInVehicles="0.53" meanMaxJamLengthInMeters="3.20" maxJamLengthInVehicles="3" maxJamLengthInMeters="21.00" jamLengthInVehiclesSum="53" jamLengthInMetersSum="319.69" meanHaltingDuration="14.25" maxHaltingDuration="30.00" haltingDurationSum="57.00" meanIntervalHaltingDuration="14.25" maxIntervalHaltingDuration="30.00" intervalHaltingDurationSum="57.00" startedHalts="4.00" meanVehicleNumber="0.87" maxVehicleNumber="4" />
   <interval begin="600.00" end="700.00" id="laneAreaDetector.E3" sampledSeconds="215.43" nVehEntered="11" nVehLeft="8" nVehSeen="11" meanSpeed="3.35" meanTimeLoss="15.24" meanOccupancy="5.22" maxOccupancy="15.00" meanMaxJamLengthInVehicles="1.22" meanMaxJamLengthInMeters="8.00" maxJamLengthInVehicles="6" maxJamLengthInMeters="43.52" jamLengthInVehiclesSum="122" jamLengthInMetersSum="800.09" meanHaltingDuration="14.55" maxHaltingDuration="29.00" haltingDurationSum="131.00" meanIntervalHaltingDuration="14.55" maxIntervalHaltingDuration="29.00" intervalHaltingDurationSum="131.00" startedHalts="9.00" meanVehicleNumber="2.21" maxVehicleNumber="6" />
   <interval begin="700.00" end="800.00" id="laneAreaDetector.E3" sampledSeconds="239.54" nVehEntered="7" nVehLeft="9" nVehSeen="10" meanSpeed="2.24" meanTimeLoss="20.35" meanOccupancy="5.80" maxOccupancy="17.50" meanMaxJamLengthInVehicles="1.66" meanMaxJamLengthInMeters="11.43" maxJamLengthInVehicles="7" maxJamLengthInMeters="51.02" jamLengthInVehiclesSum="166" jamLengthInMetersSum="1142.86" meanHaltingDuration="24.38" maxHaltingDuration="48.00" haltingDurationSum="195.00" meanIntervalHaltingDuration="21.38" maxIntervalHaltingDuration="35.00" intervalHaltingDurationSum="171.00" startedHalts="5.00" meanVehicleNumber="2.42" maxVehicleNumber="7" />
   <interval begin="800.00" end="900.00" id="laneAreaDetector.E3" sampledSeconds="188.72" nVehEntered="10" nVehLeft="7" nVehSeen="11" meanSpeed="2.02" meanTimeLoss="14.88" meanOccupancy="4.59" maxOccupancy="10.00" meanMaxJamLengthInVehicles="1.29" meanMaxJamLengthInMeters="8.16" maxJamLengthInVehicles="4" maxJamLengthInMeters="27.69" jamLengthInVehiclesSum="129" jamLengthInMetersSum="815.61" meanHaltingDuration="20.00" maxHaltingDuration="36.00" haltingDurationSum="140.00" meanIntervalHaltingDuration="19.29" maxIntervalHaltingDuration="31.00" intervalHaltingDurationSum="135.00" startedHalts="6.00" meanVehicleNumber="1.93" maxVehicleNumber="5" />
   <interval begin="900.00" end="1000.00" id="laneAreaDetector.E3" sampledSeconds="261.64" nVehEntered="9" nVehLeft="9" nVehSeen="13" meanSpeed="1.51" meanTimeLoss="18.06" meanOccupancy="6.36" maxOccupancy="15.00" meanMaxJamLengthInVehicles="1.89" meanMaxJamLengthInMeters="12.72" maxJamLengthInVehicles="5" maxJamLengthInMeters="36.01" jamLengthInVehiclesSum="189" jamLengthInMetersSum="1272.38" meanHaltingDuration="22.27" maxHaltingDuration="46.00" haltingDurationSum="245.00" meanIntervalHaltingDuration="17.91" maxIntervalHaltingDuration="34.00" intervalHaltingDurationSum="197.00" startedHalts="8.00" meanVehicleNumber="2.67" maxVehicleNumber="6" />
   <interval begin="1000.00" end="1100.00" id="laneAreaDetector.E3" sampledSeconds="97.24" nVehEntered="6" nVehLeft="9" nVehSeen="10" meanSpeed="2.92" meanTimeLoss="7.75" meanOccupancy="2.28" maxOccupancy="10.00" meanMaxJamLengthInVehicles="0.49" meanMaxJamLengthInMeters="3.04" maxJamLengthInVehicles="2" maxJamLengthInMeters="13.52" jamLengthInVehiclesSum="49" jamLengthInMetersSum="303.58" meanHaltingDuration="14.00" maxHaltingDuration="24.00" haltingDurationSum="84.00" meanIntervalHaltingDuration="8.67" maxIntervalHaltingDuration="24.00" intervalHaltingDurationSum="52.00" startedHalts="3.00" meanVehicleNumber="1.02" maxVehicleNumber="4" />
   <interval begin="1100.00" end="1200.00" id="laneAreaDetector.E3" sampledSeconds="166.79" nVehEntered="7" nVehLeft="5" nVehSeen="8" meanSpeed="1.16" meanTimeLoss="19.15" meanOccupancy="4.05" maxOccupancy="10.00" meanMaxJamLengthInVehicles="1.21" meanMaxJamLengthInMeters="7.55" maxJamLengthInVehicles="4" maxJamLengthInMeters="28.63" jamLengthInVehiclesSum="121" jamLengthInMetersSum="755.01" meanHaltingDuration="18.29" maxHaltingDuration="34.00" haltingDurationSum="128.00" meanIntervalHaltingDuration="18.29" maxIntervalHaltingDuration="34.00" intervalHaltingDurationSum="128.00" startedHalts="7.00" meanVehicleNumber="1.69" maxVehicleNumber="4" />
   <interval begin="1200.00" end="1300.00" id="laneAreaDetector.E3" sampledSeconds="182.67" nVehEntered="9" nVehLeft="12" nVehSeen="12" meanSpeed="3.68" meanTimeLoss="11.45" meanOccupancy="4.32" maxOccupancy="14.70" meanMaxJamLengthInVehicles="0.93" meanMaxJamLengthInMeters="5.92" maxJamLengthInVehicles="5" maxJamLengthInMeters="35.07" jamLengthInVehiclesSum="93" jamLengthInMetersSum="592.09" meanHaltingDuration="18.62" maxHaltingDuration="37.00" haltingDurationSum="149.00" meanIntervalHaltingDuration="12.25" maxIntervalHaltingDuration="37.00" intervalHaltingDurationSum="98.00" startedHalts="5.00" meanVehicleNumber="1.90" maxVehicleNumber="6" />
   <interval begin="1300.00" end="1400.00" id="laneAreaDetector.E3" sampledSeconds="18.67" nVehEntered="2" nVehLeft="2" nVehSeen="2" meanSpeed="2.50" meanTimeLoss="7.76" meanOccupancy="0.41" maxOccupancy="4.76" meanMaxJamLengthInVehicles="0.08" meanMaxJamLengthInMeters="0.40" maxJamLengthInVehicles="1" maxJamLengthInMeters="5.00" jamLengthInVehiclesSum="8" jamLengthInMetersSum="40.00" meanHaltingDuration="9.00" maxHaltingDuration="9.00" haltingDurationSum="9.00" meanIntervalHaltingDuration="9.00" maxIntervalHaltingDuration="9.00" intervalHaltingDurationSum="9.00" startedHalts="1.00" meanVehicleNumber="0.20" maxVehicleNumber="2" />
   <interval begin="1400.00" end="1500.00" id="laneAreaDetector.E3" sampledSeconds="26.17" nVehEntered="5" nVehLeft="5" nVehSeen="5" meanSpeed="3.27" meanTimeLoss="4.01" meanOccupancy="0.54" maxOccupancy="3.11" meanMaxJamLengthInVehicles="0.13" meanMaxJamLengthInMeters="0.65" maxJamLengthInVehicles="1" maxJamLengthInMeters="5.00" jamLengthInVehiclesSum="13" jamLengthInMetersSum="65.00" meanHaltingDuration="14.00" maxHaltingDuration="14.00" haltingDurationSum="14.00" meanIntervalHaltingDuration="14.00" maxIntervalHaltingDuration="14.00" intervalHaltingDurationSum="14.00" startedHalts="1.00" meanVehicleNumber="0.29" maxVehicleNumber="2" />
   <interval begin="1500.00" end="1600.00" id="laneAreaDetector.E3" sampledSeconds="74.60" nVehEntered="5" nVehLeft="5" nVehSeen="5" meanSpeed="4.29" meanTimeLoss="10.55" meanOccupancy="1.78" maxOccupancy="8.58" meanMaxJamLengthInVehicles="0.39" meanMaxJamLengthInMeters="2.34" maxJamLengthInVehicles="2" maxJamLengthInMeters="13.49" jamLengthInVehiclesSum="39" jamLengthInMetersSum="233.51" meanHaltingDuration="20.50" maxHaltingDuration="24.00" haltingDurationSum="41.00" meanIntervalHaltingDuration="20.50" maxIntervalHaltingDuration="24.00" intervalHaltingDurationSum="41.00" startedHalts="2.00" meanVehicleNumber="0.78" maxVehicleNumber="4" />
   <interval begin="1600.00" end="1700.00" id="laneAreaDetector.E3" sampledSeconds="40.88" nVehEntered="5" nVehLeft="5" nVehSeen="5" meanSpeed="2.55" meanTimeLoss="6.74" meanOccupancy="0.92" maxOccupancy="5.00" meanMaxJamLengthInVehicles="0.20" meanMaxJamLengthInMeters="1.05" maxJamLengthInVehicles="2" maxJamLengthInMeters="12.50" jamLengthInVehiclesSum="20" jamLengthInMetersSum="105.00" meanHaltingDuration="11.00" maxHaltingDuration="17.00" haltingDurationSum="22.00" meanIntervalHaltingDuration="11.00" maxIntervalHaltingDuration="17.00" intervalHaltingDurationSum="22.00" startedHalts="2.00" meanVehicleNumber="0.44" maxVehicleNumber="3" />
   <interval begin="1700.00" end="1800.00" id="laneAreaDetector.E3" sampledSeconds="79.32" nVehEntered="4" nVehLeft="4" nVehSeen="4" meanSpeed="1.66" meanTimeLoss="17.59" meanOccupancy="1.89" maxOccupancy="10.00" meanMaxJamLengthInVehicles="0.51" meanMaxJamLengthInMeters="3.19" maxJamLengthInVehicles="4" maxJamLengthInMeters="27.50" jamLengthInVehiclesSum="51" jamLengthInMetersSum="318.96" meanHaltingDuration="13.75" maxHaltingDuration="22.00" haltingDurationSum="55.00" meanIntervalHaltingDuration="13.75" maxIntervalHaltingDuration="22.00" intervalHaltingDurationSum="55.00" startedHalts="4.00" meanVehicleNumber="0.82" maxVehicleNumber="4" />
   <interval begin="1800.00" end="1900.00" id="laneAreaDetector.E3" sampledSeconds="75.37" nVehEntered="6" nVehLeft="6" nVehSeen="6" meanSpeed="4.20" meanTimeLoss="9.19" meanOccupancy="1.77" maxOccupancy="7.50" meanMaxJamLengthInVehicles="0.37" meanMaxJamLengthInMeters="2.06" maxJamLengthInVehicles="2" maxJamLengthInMeters="13.50" jamLengthInVehiclesSum="37" jamLengthInMetersSum="205.91" meanHaltingDuration="13.33" maxHaltingDuration="22.00" haltingDurationSum="40.00" meanIntervalHaltingDuration="13.33" maxIntervalHaltingDuration="22.00" intervalHaltingDurationSum="40.00" startedHalts="3.00" meanVehicleNumber="0.79" maxVehicleNumber="3" />
   <interval begin="1900.00" end="2000.00" id="laneAreaDetector.E3" sampledSeconds="54.41" nVehEntered="4" nVehLeft="4" nVehSeen="4" meanSpeed="1.80" meanTimeLoss="12.04" meanOccupancy="1.26" maxOccupancy="7.50" meanMaxJamLengthInVehicles="0.34" meanMaxJamLengthInMeters="2.01" maxJamLengthInVehicles="2" maxJamLengthInMeters="13.69" jamLengthInVehiclesSum="34" jamLengthInMetersSum="201.20" meanHaltingDuration="12.33" maxHaltingDuration="20.00" haltingDurationSum="37.00" meanIntervalHaltingDuration="12.33" maxIntervalHaltingDuration="20.00" intervalHaltingDurationSum="37.00" startedHalts="3.00" meanVehicleNumber="0.57" maxVehicleNumber="3" />
   <interval begin="2000.00" end="2001.00" id="laneAreaDetector.E3" sampledSeconds="0.00" nVehEntered="0" nVehLeft="0" nVehSeen="0" meanSpeed="-1.00" meanTimeLoss="-1.00" meanOccupancy="0.00" maxOccupancy="0.00" meanMaxJamLengthInVehicles="0.00" meanMaxJamLengthInMeters="0.00" maxJamLengthInVehicles="0" maxJamLengthInMeters="0.00" jamLengthInVehiclesSum="0" jamLengthInMetersSum="0.00" meanHaltingDuration="0.00" maxHaltingDuration="0.00" haltingDurationSum="0.00" meanIntervalHaltingDuration="0.00" maxIntervalHaltingDuration="0.00" intervalHaltingDurationSum="0.00" startedHalts="0.00" meanVehicleNumber="0.00" maxVehicleNumber="0" />
</detector>
